outgram/__init__.py
outgram/cli.py
outgram/client.py
outgram/instagram.py
outgram/models.py
outgram/threads.py
outgram/utils.py
outgram-0.1.1.dist-info/LICENSE
outgram-0.1.1.dist-info/METADATA
outgram-0.1.1.dist-info/WHEEL
outgram-0.1.1.dist-info/entry_points.txt
outgram-0.1.1.dist-info/top_level.txt
outgram-0.1.1.dist-info/RECORD
